setup.py
SlideGen.egg-info/PKG-INFO
SlideGen.egg-info/SOURCES.txt
SlideGen.egg-info/dependency_links.txt
SlideGen.egg-info/entry_points.txt
SlideGen.egg-info/requires.txt
SlideGen.egg-info/top_level.txt
slidegen/Deskjs.py
slidegen/EngineFileGen.py
slidegen/SlideGen.py
slidegen/__init__.py