Metadata-Version: 1.0
Name: SlideGen
Version: 0.0.0.1.pre2
Summary: A HTML5 Slide Generator in python
Home-page: https://github.com/reyoung/SlideGen
Author: reyoung
Author-email: reyoung@126.com
License: LGPL
Keywords: html5 slide generator
Platform: UNKNOWN
